orbitaldump/__init__.py
orbitaldump/__main__.py
orbitaldump/orbitaldump.py
orbitaldump-1.0.1.dist-info/LICENSE
orbitaldump-1.0.1.dist-info/METADATA
orbitaldump-1.0.1.dist-info/WHEEL
orbitaldump-1.0.1.dist-info/entry_points.txt
orbitaldump-1.0.1.dist-info/top_level.txt
orbitaldump-1.0.1.dist-info/RECORD
