Metadata-Version: 2.1
Name: orbitaldump
Version: 1.0.1
Summary: A simple multi-threaded distributed SSH brute-forcing tool written in Python
Home-page: https://github.com/k4yt3x/orbitaldump
Author: K4YT3X
Author-email: k4yt3x@k4yt3x.com
License: GNU General Public License v3.0
Platform: UNKNOWN
Classifier: Topic :: Security
Classifier: Environment :: Console
Classifier: Programming Language :: Python
Classifier: Programming Language :: Python :: 3
Classifier: Operating System :: OS Independent
Requires-Python: >=3.7
Requires-Dist: PySocks
Requires-Dist: loguru
Requires-Dist: paramiko
Requires-Dist: requests
